{
  "version": "7",
  "dialect": "postgresql",
  "entries": [
    {
      "idx": 0,
      "version": "7",
      "when": 1780926127768,
      "tag": "0000_strong_leopardon",
      "breakpoints": true
    },
    {
      "idx": 1,
      "version": "7",
      "when": 1781018194210,
      "tag": "0001_gigantic_groot",
      "breakpoints": true
    },
    {
      "idx": 2,
      "version": "7",
      "when": 1781354562127,
      "tag": "0002_bright_frank_castle",
      "breakpoints": true
    },
    {
      "idx": 3,
      "version": "7",
      "when": 1781493420566,
      "tag": "0003_ambiguous_stryfe",
      "breakpoints": true
    },
    {
      "idx": 4,
      "version": "7",
      "when": 1781508084196,
      "tag": "0004_sharp_silver_fox",
      "breakpoints": true
    },
    {
      "idx": 5,
      "version": "7",
      "when": 1781534354709,
      "tag": "0005_steady_dakota_north",
      "breakpoints": true
    },
    {
      "idx": 6,
      "version": "7",
      "when": 1783050621070,
      "tag": "0006_living_skin",
      "breakpoints": true
    }
  ]
}